[
  {
    "title": "IAM Business Analyst",
    "company": "Cognisol",
    "description": "Job Description Job Description Job Title : IAM Business Analyst Client : Bank of New York Mellon Corp Experience: 5 yrs Notice: Immediate Client Location : & Pittsburgh, PA OR Nashville, TN OR Lake Mary, FL (Need Local Candidates only) Interview Type : Webcam Work Mode : Hybrid Contract for 12 months Note : Local to PA/TN/FL Preferred Banking experience preferred. Must Have: SailPoint IIQ, IAM, Cybersecurity If Interested, please share your resume to divya.scognisolglobal.com Key Responsibilit\u2026",
    "location": "Oley Furnace, Berks County",
    "posted_date": "2025-04-19T12:06:54Z",
    "url": "https://www.adzuna.com/land/ad/5153341941?se=ioQiT38d8BG-i3PTGXcHCQ&utm_medium=api&utm_source=71cf92b8&v=51CE45BD277DAF62DB96AF76EF6ADF3D2CC51C72",
    "skills": [],
    "salary_range": "\u00a383,930 - \u00a383,930",
    "is_remote": false,
    "matched_keywords": [
      "rest",
      "it",
      "web",
      "business",
      "analyst"
    ]
  }
]